five_card_draw/fcd_bank.txt
five_card_draw/fcd_functions.py
five_card_draw/fcd_pagegui.py
five_card_draw/poker_start.py
five_card_draw/data/C10.png
five_card_draw/data/C11.png
five_card_draw/data/C12.png
five_card_draw/data/C13.png
five_card_draw/data/C14.png
five_card_draw/data/C2.png
five_card_draw/data/C3.png
five_card_draw/data/C4.png
five_card_draw/data/C5.png
five_card_draw/data/C6.png
five_card_draw/data/C7.png
five_card_draw/data/C8.png
five_card_draw/data/C9.png
five_card_draw/data/CardBack.png
five_card_draw/data/D10.png
five_card_draw/data/D11.png
five_card_draw/data/D12.png
five_card_draw/data/D13.png
five_card_draw/data/D14.png
five_card_draw/data/D2.png
five_card_draw/data/D3.png
five_card_draw/data/D4.png
five_card_draw/data/D5.png
five_card_draw/data/D6.png
five_card_draw/data/D7.png
five_card_draw/data/D8.png
five_card_draw/data/D9.png
five_card_draw/data/H10.png
five_card_draw/data/H11.png
five_card_draw/data/H12.png
five_card_draw/data/H13.png
five_card_draw/data/H14.png
five_card_draw/data/H2.png
five_card_draw/data/H3.png
five_card_draw/data/H4.png
five_card_draw/data/H5.png
five_card_draw/data/H6.png
five_card_draw/data/H7.png
five_card_draw/data/H8.png
five_card_draw/data/H9.png
five_card_draw/data/S10.png
five_card_draw/data/S11.png
five_card_draw/data/S12.png
five_card_draw/data/S13.png
five_card_draw/data/S14.png
five_card_draw/data/S2.png
five_card_draw/data/S3.png
five_card_draw/data/S4.png
five_card_draw/data/S5.png
five_card_draw/data/S6.png
five_card_draw/data/S7.png
five_card_draw/data/S8.png
five_card_draw/data/S9.png
five_card_draw/data/ScoringImage.png
five_card_draw/data/black_joker.png
five_card_draw/data/red_joker.png
five_card_draw-1.1.0.data/scripts/poker_start.py
five_card_draw-1.1.0.dist-info/LICENSE.txt
five_card_draw-1.1.0.dist-info/METADATA
five_card_draw-1.1.0.dist-info/WHEEL
five_card_draw-1.1.0.dist-info/top_level.txt
five_card_draw-1.1.0.dist-info/RECORD
