Metadata-Version: 2.1
Name: five-card-draw
Version: 1.1.0
Summary: 5 Card Draw Video Poker application
Home-page: https://github.com/ralbee1/5_card_draw
Author: Richard Albee
Author-email: Ralbee1@iwu.edu
License: LICENSE.txt
License-File: LICENSE.txt
Requires-Dist: tk
Requires-Dist: pathlib
